Metadata-Version: 2.1
Name: passconfig
Version: 1.0.0
Summary: A Simple Username and Password Manager
Home-page: https://github.com/suqingdong/passconfig
Author: suqingdong
Author-email: 1078595229@qq.com
License: BSD License
Platform: UNKNOWN
Classifier: Development Status :: 5 - Production/Stable
Classifier: Operating System :: OS Independent
Classifier: Intended Audience :: Developers
Classifier: License :: OSI Approved :: BSD License
Classifier: Programming Language :: Python
Classifier: Programming Language :: Python :: 2
Classifier: Programming Language :: Python :: 2.7
Classifier: Programming Language :: Python :: 3
Classifier: Programming Language :: Python :: 3.6
Classifier: Topic :: Software Development :: Libraries
